setup.py
get_time_zzs/__init__.py
get_time_zzs.egg-info/PKG-INFO
get_time_zzs.egg-info/SOURCES.txt
get_time_zzs.egg-info/dependency_links.txt
get_time_zzs.egg-info/entry_points.txt
get_time_zzs.egg-info/top_level.txt