Metadata-Version: 2.1
Name: get-time-zzs
Version: 0.0.4
Summary: 获取任意时间/获取当前的时间戳/时间转时间戳/时间戳转时间
Home-page: https://github.com/Coxhuang/get_time
Author: sss
Author-email: ssss@gmail.com
License: UNKNOWN
Platform: UNKNOWN
